{"chunk_definitions":[{"row":78,"row_count":1,"visible":true,"expansion_state":0,"options":{"engine":"r","label":"unnamed-chunk-3"},"document_id":"4E752CB2","chunk_id":"c0e5b7ivlpi00","chunk_label":"unnamed-chunk-5"},{"row":101,"row_count":1,"visible":true,"expansion_state":0,"options":{"engine":"r","label":"unnamed-chunk-4"},"document_id":"4E752CB2","chunk_id":"c1ri9ejqj4bdv","chunk_label":"unnamed-chunk-6"},{"row":131,"row_count":1,"visible":true,"expansion_state":0,"options":{"engine":"r","label":"unnamed-chunk-7"},"document_id":"4E752CB2","chunk_id":"cwoxj07v2tfsh","chunk_label":"unnamed-chunk-7"},{"row":159,"row_count":1,"visible":true,"expansion_state":0,"options":{"engine":"r","label":"unnamed-chunk-8"},"document_id":"4E752CB2","chunk_id":"cx7fwcu33apix","chunk_label":"unnamed-chunk-9"},{"row":252,"row_count":1,"visible":true,"expansion_state":0,"options":{"engine":"r","label":"unnamed-chunk-1"},"document_id":"4E752CB2","chunk_id":"ckyevnbkxsrut","chunk_label":"unnamed-chunk-15"},{"row":263,"row_count":1,"visible":true,"expansion_state":0,"options":{"engine":"r","label":"unnamed-chunk-2"},"document_id":"4E752CB2","chunk_id":"cxzn3u32vpbpz","chunk_label":"unnamed-chunk-16"}],"doc_write_time":1672214012}